{
  "user_id": "Dusan.Gonda",
  "name": "Ing. Dušan Gonda",
  "public_function": "štatutárny orgán alebo člen štatutárneho orgánu a člen riadiaceho orgánu právnickej osoby (INŠPEKTORÁT PRÁCE BANSKÁ BYSTRICA\r\n)",
  "years": [
    2023,
    2024
  ],
  "timeline": [
    {
      "year": 2023,
      "data": {
        "id": "ZC245844",
        "declaration_id": 30031,
        "name": "Ing. DUŠAN GONDA",
        "year": 2023,
        "filed": "pri ujatí sa funkcie",
        "public_function": "štatutárny orgán alebo člen štatutárneho orgánu a člen riadiaceho orgánu právnickej osoby (INŠPEKTORÁT PRÁCE BANSKÁ BYSTRICA)",
        "income": {
          "public_function": 0,
          "other": 0
        },
        "incompatibility": true,
        "employment": "INŠPEKTORÁT PRÁCE BANSKÁ BYSTRICA\nDlhodobo plne uvoľnený na výkon verejnej funkcie podľa Zákonníka práce:\náno",
        "business_activity": null,
        "positions": null,
        "real_estate": [
          {
            "type": "RODINNÝ DOM",
            "cadastral_territory": "KREMNIČKA",
            "lv_number": "1156",
            "share": "1/4"
          },
          {
            "type": "ORNÁ PÔDA",
            "cadastral_territory": "KREMNIČKA",
            "lv_number": "1557",
            "share": "1/2"
          },
          {
            "type": "URBÁR",
            "cadastral_territory": "LIPTOVSKÁ MARA",
            "lv_number": "357",
            "share": "3024/12297"
          },
          {
            "type": "URBÁR",
            "cadastral_territory": "LIPTOVSKÁ MARA",
            "lv_number": "469",
            "share": "9/324"
          },
          {
            "type": "URBÁR",
            "cadastral_territory": "LIPTOVSKÁ MARA",
            "lv_number": "468",
            "share": "14/324"
          },
          {
            "type": "URBÁR",
            "cadastral_territory": "LIPTOVSKÁ MARA",
            "lv_number": "402",
            "share": "14/324"
          },
          {
            "type": "ORNÁ PÔDA URBÁR",
            "cadastral_territory": "LIPTOVSKÁ MARA",
            "lv_number": "376",
            "share": "18/324"
          },
          {
            "type": "PASIENKY",
            "cadastral_territory": "BOBROVNÍK",
            "lv_number": "562",
            "share": "1/3"
          },
          {
            "type": "URBÁR",
            "cadastral_territory": "LIPTOVSKÁ MARA",
            "lv_number": "403",
            "share": "14/324"
          }
        ],
        "movable_property": [
          {
            "type": "OSOBNÉ VOZIDLO",
            "brand": "BMW",
            "year_of_manufacture": 2014,
            "share": "1/1"
          },
          {
            "type": "OSOBNÉ VOZIDLO",
            "brand": "OPEL",
            "year_of_manufacture": 2014,
            "share": "1/1"
          }
        ],
        "property_rights": null,
        "obligations": [
          {
            "type": "žiadny"
          }
        ],
        "use_of_others_real_estate": null,
        "vehicles": null,
        "gifts": null
      },
      "diff": {
        "type": "new"
      }
    },
    {
      "year": 2024,
      "data": {
        "id": "ZC245844",
        "declaration_id": 37613,
        "name": "Ing. DUŠAN GONDA",
        "year": 2024,
        "filed": "k 30. aprílu",
        "public_function": "štatutárny orgán alebo člen štatutárneho orgánu a člen riadiaceho orgánu právnickej osoby (INŠPEKTORÁT PRÁCE BANSKÁ BYSTRICA\r\n)",
        "income": {
          "public_function": 38542,
          "other": 0
        },
        "incompatibility": true,
        "employment": "INŠPEKTORÁT PRÁCE BANSKÁ BYSTRICA\nDlhodobo plne uvoľnený na výkon verejnej funkcie podľa Zákonníka práce:\náno",
        "business_activity": null,
        "positions": null,
        "real_estate": [
          {
            "type": "ORNÁ PÔDA URBÁR",
            "cadastral_territory": "LIPTOVSKÁ MARA",
            "lv_number": "376",
            "share": "18/324"
          },
          {
            "type": "PASIENKY",
            "cadastral_territory": "BOBROVNÍK",
            "lv_number": "562",
            "share": "1/3"
          },
          {
            "type": "URBÁR",
            "cadastral_territory": "LIPTOVSKÁ MARA",
            "lv_number": "403",
            "share": "14/324"
          },
          {
            "type": "RODINNÝ DOM",
            "cadastral_territory": "KREMNIČKA",
            "lv_number": "1156",
            "share": "1/4"
          },
          {
            "type": "ORNÁ PÔDA",
            "cadastral_territory": "KREMNIČKA",
            "lv_number": "1557",
            "share": "1/2"
          },
          {
            "type": "URBÁR",
            "cadastral_territory": "LIPTOVSKÁ MARA",
            "lv_number": "357",
            "share": "3024/12297"
          },
          {
            "type": "URBÁR",
            "cadastral_territory": "LIPTOVSKÁ MARA",
            "lv_number": "469",
            "share": "9/324"
          },
          {
            "type": "URBÁR",
            "cadastral_territory": "LIPTOVSKÁ MARA",
            "lv_number": "468",
            "share": "14/324"
          },
          {
            "type": "URBÁR",
            "cadastral_territory": "LIPTOVSKÁ MARA",
            "lv_number": "402",
            "share": "14/324"
          }
        ],
        "movable_property": [
          {
            "type": "OSOBNÉ VOZIDLO",
            "brand": "BMW",
            "year_of_manufacture": 2014,
            "share": "1/1"
          },
          {
            "type": "OSOBNÉ VOZIDLO",
            "brand": "BMW",
            "year_of_manufacture": 2016,
            "share": "1/1"
          }
        ],
        "property_rights": null,
        "obligations": [
          {
            "type": "žiadny"
          }
        ],
        "use_of_others_real_estate": null,
        "vehicles": null,
        "gifts": null
      },
      "diff": {
        "type": "changed",
        "changes": [
          {
            "field": "public_function",
            "old": "štatutárny orgán alebo člen štatutárneho orgánu a člen riadiaceho orgánu právnickej osoby (INŠPEKTORÁT PRÁCE BANSKÁ BYSTRICA)",
            "new": "štatutárny orgán alebo člen štatutárneho orgánu a člen riadiaceho orgánu právnickej osoby (INŠPEKTORÁT PRÁCE BANSKÁ BYSTRICA\r\n)"
          },
          {
            "field": "income",
            "old": {
              "public_function": 0,
              "other": 0
            },
            "new": {
              "public_function": 38542,
              "other": 0
            },
            "old_total": 0,
            "new_total": 38542,
            "delta": 38542
          },
          {
            "field": "real_estate",
            "old": [
              {
                "type": "RODINNÝ DOM",
                "cadastral_territory": "KREMNIČKA",
                "lv_number": "1156",
                "share": "1/4"
              },
              {
                "type": "ORNÁ PÔDA",
                "cadastral_territory": "KREMNIČKA",
                "lv_number": "1557",
                "share": "1/2"
              },
              {
                "type": "URBÁR",
                "cadastral_territory": "LIPTOVSKÁ MARA",
                "lv_number": "357",
                "share": "3024/12297"
              },
              {
                "type": "URBÁR",
                "cadastral_territory": "LIPTOVSKÁ MARA",
                "lv_number": "469",
                "share": "9/324"
              },
              {
                "type": "URBÁR",
                "cadastral_territory": "LIPTOVSKÁ MARA",
                "lv_number": "468",
                "share": "14/324"
              },
              {
                "type": "URBÁR",
                "cadastral_territory": "LIPTOVSKÁ MARA",
                "lv_number": "402",
                "share": "14/324"
              },
              {
                "type": "ORNÁ PÔDA URBÁR",
                "cadastral_territory": "LIPTOVSKÁ MARA",
                "lv_number": "376",
                "share": "18/324"
              },
              {
                "type": "PASIENKY",
                "cadastral_territory": "BOBROVNÍK",
                "lv_number": "562",
                "share": "1/3"
              },
              {
                "type": "URBÁR",
                "cadastral_territory": "LIPTOVSKÁ MARA",
                "lv_number": "403",
                "share": "14/324"
              }
            ],
            "new": [
              {
                "type": "ORNÁ PÔDA URBÁR",
                "cadastral_territory": "LIPTOVSKÁ MARA",
                "lv_number": "376",
                "share": "18/324"
              },
              {
                "type": "PASIENKY",
                "cadastral_territory": "BOBROVNÍK",
                "lv_number": "562",
                "share": "1/3"
              },
              {
                "type": "URBÁR",
                "cadastral_territory": "LIPTOVSKÁ MARA",
                "lv_number": "403",
                "share": "14/324"
              },
              {
                "type": "RODINNÝ DOM",
                "cadastral_territory": "KREMNIČKA",
                "lv_number": "1156",
                "share": "1/4"
              },
              {
                "type": "ORNÁ PÔDA",
                "cadastral_territory": "KREMNIČKA",
                "lv_number": "1557",
                "share": "1/2"
              },
              {
                "type": "URBÁR",
                "cadastral_territory": "LIPTOVSKÁ MARA",
                "lv_number": "357",
                "share": "3024/12297"
              },
              {
                "type": "URBÁR",
                "cadastral_territory": "LIPTOVSKÁ MARA",
                "lv_number": "469",
                "share": "9/324"
              },
              {
                "type": "URBÁR",
                "cadastral_territory": "LIPTOVSKÁ MARA",
                "lv_number": "468",
                "share": "14/324"
              },
              {
                "type": "URBÁR",
                "cadastral_territory": "LIPTOVSKÁ MARA",
                "lv_number": "402",
                "share": "14/324"
              }
            ],
            "old_count": 9,
            "new_count": 9
          },
          {
            "field": "movable_property",
            "old": [
              {
                "type": "OSOBNÉ VOZIDLO",
                "brand": "BMW",
                "year_of_manufacture": 2014,
                "share": "1/1"
              },
              {
                "type": "OSOBNÉ VOZIDLO",
                "brand": "OPEL",
                "year_of_manufacture": 2014,
                "share": "1/1"
              }
            ],
            "new": [
              {
                "type": "OSOBNÉ VOZIDLO",
                "brand": "BMW",
                "year_of_manufacture": 2014,
                "share": "1/1"
              },
              {
                "type": "OSOBNÉ VOZIDLO",
                "brand": "BMW",
                "year_of_manufacture": 2016,
                "share": "1/1"
              }
            ],
            "old_count": 2,
            "new_count": 2
          }
        ]
      }
    }
  ],
  "total_changes": 4,
  "slug": "ing-dusan-gonda"
}