{
  "user_id": "Igor.Dusenka",
  "name": "JUDr. Igor Dušenka",
  "public_function": "poslanec Národnej rady Slovenskej republiky",
  "years": [
    2024
  ],
  "timeline": [
    {
      "year": 2024,
      "data": {
        "id": "B256603",
        "declaration_id": 36701,
        "name": "JUDr. IGOR DUŠENKA",
        "year": 2024,
        "filed": "pri ujatí sa funkcie",
        "public_function": "poslanec Národnej rady Slovenskej republiky",
        "income": {
          "public_function": 0,
          "other": 0
        },
        "incompatibility": true,
        "employment": null,
        "business_activity": null,
        "positions": null,
        "real_estate": [
          {
            "type": "BYT",
            "cadastral_territory": "RUŽINOV",
            "lv_number": "4507",
            "share": "1/1 BSM"
          }
        ],
        "movable_property": null,
        "property_rights": [
          "BANKOVÝ ÚČET, podiel: BSM"
        ],
        "obligations": [
          {
            "type": "HYPOTEKÁRNY ÚVER",
            "share": "BSM",
            "date": "25. 08. 2021"
          }
        ],
        "use_of_others_real_estate": null,
        "vehicles": null,
        "gifts": null
      },
      "diff": {
        "type": "new"
      }
    }
  ],
  "total_changes": 0,
  "slug": "judr-igor-dusenka"
}