{
  "user_id": "Radoslav.Kasander",
  "name": "Ing. Radoslav Kasander",
  "public_function": "člen dozornej rady Všeobecnej zdravotnej poisťovne",
  "years": [
    2023,
    2024
  ],
  "timeline": [
    {
      "year": 2023,
      "data": {
        "id": "X246260",
        "declaration_id": 32423,
        "name": "Ing. RADOSLAV KASANDER",
        "year": 2023,
        "filed": "pri ujatí sa funkcie",
        "public_function": "člen dozornej rady Všeobecnej zdravotnej poisťovne",
        "income": {
          "public_function": 0,
          "other": 0
        },
        "incompatibility": true,
        "employment": "ÚRAD PRE REGULÁCIU SIEŤOVÝCH ODVETVÍ\nDlhodobo plne uvoľnený na výkon verejnej funkcie podľa Zákonníka práce:\nnie",
        "business_activity": null,
        "positions": null,
        "real_estate": [
          {
            "type": "POZEMOK",
            "cadastral_territory": "CHORVÁTSKY GROB",
            "lv_number": "1656/332",
            "share": "BSM"
          },
          {
            "type": "DOM",
            "cadastral_territory": "CHORVÁTSKY GROB",
            "lv_number": "1656/173",
            "share": "BSM"
          },
          {
            "type": "BYT",
            "cadastral_territory": "NIVY",
            "lv_number": "1954",
            "share": "BSM"
          }
        ],
        "movable_property": [
          {
            "type": "AUTO",
            "brand": "VOLKSWAGEN",
            "year_of_manufacture": 2017,
            "share": "BSM"
          }
        ],
        "property_rights": [
          "FINANČNÉ PROSTRIEDKY, podiel: BSM",
          "AKCIE, podiel: BSM"
        ],
        "obligations": [
          {
            "type": "žiadny"
          }
        ],
        "use_of_others_real_estate": null,
        "vehicles": null,
        "gifts": null
      },
      "diff": {
        "type": "new"
      }
    },
    {
      "year": 2024,
      "data": {
        "id": "X246260",
        "declaration_id": 37502,
        "name": "Ing. RADOSLAV KASANDER",
        "year": 2024,
        "filed": "k 30. aprílu",
        "public_function": "člen dozornej rady Všeobecnej zdravotnej poisťovne",
        "income": {
          "public_function": 0,
          "other": 52684
        },
        "incompatibility": true,
        "employment": "ÚRAD PRE REGULÁCIU SIEŤOVÝCH ODVETVÍ\nDlhodobo plne uvoľnený na výkon verejnej funkcie podľa Zákonníka práce:\nnie",
        "business_activity": null,
        "positions": null,
        "real_estate": [
          {
            "type": "POZEMOK",
            "cadastral_territory": "CHORVÁTSKY GROB",
            "lv_number": "1656/332",
            "share": "BSM"
          },
          {
            "type": "DOM",
            "cadastral_territory": "CHORVÁTSKY GROB",
            "lv_number": "1656/173",
            "share": "BSM"
          },
          {
            "type": "BYT",
            "cadastral_territory": "NIVY",
            "lv_number": "1954",
            "share": "BSM"
          }
        ],
        "movable_property": [
          {
            "type": "AUTO",
            "brand": "VOLKSWAGEN",
            "year_of_manufacture": 2017,
            "share": "BSM"
          }
        ],
        "property_rights": [
          "FINANČNÉ PROSTRIEDKY, podiel: BSM",
          "AKCIE, podiel: BSM"
        ],
        "obligations": [
          {
            "type": "HYPOTÉKA",
            "share": "50%",
            "date": "08. 04. 2011"
          },
          {
            "type": "AMERICKÁ HYPOTÉKA",
            "share": "50%",
            "date": "04. 10. 2019"
          }
        ],
        "use_of_others_real_estate": null,
        "vehicles": null,
        "gifts": null
      },
      "diff": {
        "type": "changed",
        "changes": [
          {
            "field": "income",
            "old": {
              "public_function": 0,
              "other": 0
            },
            "new": {
              "public_function": 0,
              "other": 52684
            },
            "old_total": 0,
            "new_total": 52684,
            "delta": 52684
          },
          {
            "field": "obligations",
            "old": [
              {
                "type": "žiadny"
              }
            ],
            "new": [
              {
                "type": "HYPOTÉKA",
                "share": "50%",
                "date": "08. 04. 2011"
              },
              {
                "type": "AMERICKÁ HYPOTÉKA",
                "share": "50%",
                "date": "04. 10. 2019"
              }
            ],
            "old_count": 1,
            "new_count": 2
          }
        ]
      }
    }
  ],
  "total_changes": 2,
  "slug": "ing-radoslav-kasander"
}